{"name":"Most A Grade Finals","headers":{"c1":"Name","c2":"Finals"},"info":"Includes all A Grade Finals from 2007 to 2025","data":[{"id":2479,"n":"DAVID KEARSLEY","a":31,"c":true,"lm":true},{"id":3915,"n":"BRAD KIRK","a":26,"c":true,"lm":true},{"id":2826,"n":"BRAYDEN HEYWARD-FERORS","a":24,"c":true,"lm":false},{"id":2811,"n":"MICHAEL SHEARER","a":23,"c":true,"lm":true},{"id":2613,"n":"SAMUEL SMITH","a":23,"c":false,"lm":true},{"id":2249,"n":"DANIEL BUTCHER","a":20,"c":true,"lm":true},{"id":3119,"n":"BRADLEY PATTERSON","a":19,"c":true,"lm":false},{"id":3099,"n":"RYAN MOUNTFORD","a":16,"c":true,"lm":false},{"id":2908,"n":"LUKE BEENHAM","a":15,"c":true,"lm":false},{"id":3405,"n":"MITCHELL JOHNSON","a":15,"c":true,"lm":false},{"id":3426,"n":"SAMUEL THARALDSEN","a":15,"c":true,"lm":false},{"id":2747,"n":"ANDREW SHEARER","a":12,"c":true,"lm":false},{"id":3157,"n":"MAX RENFREY","a":12,"c":false,"lm":false},{"id":2867,"n":"NATHAN BEENHAM","a":12,"c":true,"lm":false},{"id":2847,"n":"SHANE HEATLEY","a":12,"c":false,"lm":false},{"id":2475,"n":"STEVEN GATER","a":12,"c":false,"lm":false},{"id":2834,"n":"JOSHUA VANDERMEER","a":10,"c":false,"lm":false},{"id":2871,"n":"KOBE CAVOURAS","a":10,"c":true,"lm":false},{"id":4206,"n":"BEN ROSSI","a":9,"c":true,"lm":false},{"id":2915,"n":"CASEY DAVIES","a":9,"c":true,"lm":false},{"id":3037,"n":"MACKENZIE SHORT","a":9,"c":true,"lm":false},{"id":2572,"n":"MATT CAREY","a":9,"c":false,"lm":false},{"id":2532,"n":"MATTHEW JOSE","a":9,"c":false,"lm":false},{"id":3917,"n":"MITCHELL FAZEKAS","a":9,"c":false,"lm":false},{"id":2366,"n":"PETER MCMASTER","a":9,"c":true,"lm":true},{"id":2728,"n":"SAMUEL OSMOND","a":9,"c":false,"lm":false},{"id":3178,"n":"BLAKE ALDRIDGE","a":8,"c":true,"lm":false},{"id":2594,"n":"CRAIG LANGCAKE","a":8,"c":true,"lm":true},{"id":3406,"n":"ETHAN WILDMAN","a":8,"c":true,"lm":false},{"id":2732,"n":"JARRAD LO BASSO","a":8,"c":false,"lm":false},{"id":4282,"n":"MATTHEW WALTON","a":8,"c":false,"lm":false},{"id":4205,"n":"TOBY MCALLISTER","a":8,"c":false,"lm":false},{"id":2913,"n":"ZAKARIA CAVOURAS","a":8,"c":false,"lm":false},{"id":4348,"n":"AIDEN GRAYSON","a":7,"c":true,"lm":false},{"id":2934,"n":"DECLAN TOMKINS","a":7,"c":true,"lm":false},{"id":2740,"n":"HUW CHANNING","a":7,"c":false,"lm":true},{"id":3551,"n":"JOSHUA ALBANESE","a":7,"c":false,"lm":false},{"id":3458,"n":"MARK HOLLIS","a":7,"c":false,"lm":false},{"id":3542,"n":"ADRIAN ALBANESE","a":6,"c":false,"lm":false},{"id":2619,"n":"ANTUN ALAVIJA","a":6,"c":false,"lm":false},{"id":4281,"n":"CHRIS PUIATTI","a":6,"c":false,"lm":false},{"id":2562,"n":"DANIEL WEBB","a":6,"c":false,"lm":false},{"id":4486,"n":"JOSHUA ROSMAN","a":6,"c":true,"lm":false},{"id":3872,"n":"MATTHEW RAITT","a":6,"c":false,"lm":false},{"id":4106,"n":"NASH MITCHELL","a":6,"c":false,"lm":false},{"id":3320,"n":"RICHARD RAY-ZWAR","a":6,"c":false,"lm":false},{"id":4379,"n":"TYNAN CARNEY","a":6,"c":true,"lm":false},{"id":2780,"n":"BLAISE TOMKINS","a":5,"c":true,"lm":true},{"id":3554,"n":"BRADLEY GROWDEN","a":5,"c":false,"lm":false},{"id":2176,"n":"SAUL ABBOTT","a":5,"c":false,"lm":true},{"id":2587,"n":"SHANE HEINRICH","a":5,"c":false,"lm":false},{"id":2625,"n":"THOMAS CHAPMAN","a":5,"c":false,"lm":false},{"id":2308,"n":"WAYNE COLLINGS","a":5,"c":false,"lm":false},{"id":3250,"n":"ADAM BUNWORTH","a":4,"c":true,"lm":false},{"id":2670,"n":"ANTHONY BROWNE","a":4,"c":false,"lm":false},{"id":2769,"n":"CHAD HAMP","a":4,"c":false,"lm":false},{"id":3456,"n":"CHOL MAJOK","a":4,"c":false,"lm":false},{"id":3167,"n":"DANE SOMMERS","a":4,"c":false,"lm":false},{"id":3033,"n":"D'ARCY MITCHELL","a":4,"c":true,"lm":false},{"id":3261,"n":"JORDAN JOHNS","a":4,"c":false,"lm":false},{"id":2844,"n":"LEIGH WARD","a":4,"c":false,"lm":false},{"id":2787,"n":"MITCHELL EDWARDS","a":4,"c":false,"lm":false},{"id":2541,"n":"PAUL MELLEN","a":4,"c":false,"lm":false},{"id":2643,"n":"PETER MASIKA","a":4,"c":false,"lm":false},{"id":3168,"n":"THOMAS DIXON","a":4,"c":false,"lm":false},{"id":4535,"n":"CALEB MCCORMICK","a":3,"c":true,"lm":false},{"id":3042,"n":"CHRISTOPHER BUERSCH","a":3,"c":false,"lm":false},{"id":4065,"n":"CODY SCHORN","a":3,"c":false,"lm":false},{"id":2496,"n":"DERMOTT TAYLOR","a":3,"c":false,"lm":false},{"id":4100,"n":"ETHAN JOHNSON","a":3,"c":true,"lm":false},{"id":2734,"n":"JAMIE DELL","a":3,"c":false,"lm":false},{"id":4534,"n":"JORDAN ETTO","a":3,"c":false,"lm":false},{"id":4325,"n":"MILES SUMNER","a":3,"c":false,"lm":false},{"id":2859,"n":"REECE MILSOM","a":3,"c":true,"lm":false},{"id":2540,"n":"TIM MEINECKE","a":3,"c":false,"lm":false},{"id":4004,"n":"TOM STARKEY","a":3,"c":false,"lm":false},{"id":3180,"n":"TRISTAN SMITH","a":3,"c":true,"lm":false},{"id":2583,"n":"ANGUS FISHER","a":2,"c":false,"lm":true},{"id":3707,"n":"BENJAMIN JEFFRIES","a":2,"c":true,"lm":false},{"id":2786,"n":"BRENDAN HILLIER","a":2,"c":false,"lm":false},{"id":3081,"n":"COOPER GILBERT","a":2,"c":false,"lm":false},{"id":2885,"n":"DANIEL NASH","a":2,"c":true,"lm":false},{"id":2382,"n":"DAVID STEVENS","a":2,"c":false,"lm":false},{"id":2735,"n":"HARRISON GEBHARDT","a":2,"c":false,"lm":false},{"id":2730,"n":"JAKE VANDERMEER","a":2,"c":false,"lm":false},{"id":3709,"n":"JARRAD POMEROY","a":2,"c":false,"lm":false},{"id":3696,"n":"JERICHO JOHN","a":2,"c":false,"lm":false},{"id":4113,"n":"JOSHUA BYERLEE","a":2,"c":false,"lm":false},{"id":3291,"n":"JOSHUA FAIZAL","a":2,"c":true,"lm":false},{"id":3873,"n":"NICK BAILEY","a":2,"c":false,"lm":false},{"id":4485,"n":"SAM JACOBS","a":2,"c":false,"lm":false},{"id":4107,"n":"SAM STEED","a":2,"c":false,"lm":false},{"id":2827,"n":"SAMUEL HIOSAN","a":2,"c":false,"lm":false},{"id":3427,"n":"SCOTT KUMNICK","a":2,"c":false,"lm":false},{"id":2571,"n":"ALEX CAREY","a":1,"c":false,"lm":false},{"id":3175,"n":"BEN BURBRIDGE","a":1,"c":true,"lm":false},{"id":2935,"n":"BEN PAPPS","a":1,"c":false,"lm":false},{"id":2373,"n":"BRANT RAMAGE","a":1,"c":false,"lm":false},{"id":2932,"n":"BRAYDEN ROBERTS","a":1,"c":false,"lm":false},{"id":4484,"n":"CAMERON BLAKE","a":1,"c":true,"lm":false},{"id":2473,"n":"CAMERON DIENELT","a":1,"c":false,"lm":false},{"id":1841,"n":"DAVID SMITH","a":1,"c":false,"lm":true},{"id":3093,"n":"JAKE BUNWORTH","a":1,"c":true,"lm":false},{"id":3375,"n":"JAMES BRENNAN","a":1,"c":true,"lm":false},{"id":2156,"n":"JAMES ROBSHAW","a":1,"c":false,"lm":true},{"id":4615,"n":"JESSE SCHEFE","a":1,"c":true,"lm":false},{"id":2175,"n":"KANE ABBOTT","a":1,"c":false,"lm":true},{"id":4066,"n":"LEITH (JNR) MITCHELL","a":1,"c":false,"lm":false},{"id":2416,"n":"LUKE HILL","a":1,"c":false,"lm":false},{"id":4456,"n":"MASON CARNEY","a":1,"c":true,"lm":false},{"id":2911,"n":"MATTHEW CAIRE","a":1,"c":true,"lm":false},{"id":2362,"n":"MATTHEW LENDRUM","a":1,"c":false,"lm":true},{"id":2564,"n":"MATTHEW WILLOUGHBY","a":1,"c":false,"lm":false},{"id":2720,"n":"PETER NUGENT","a":1,"c":false,"lm":false},{"id":3184,"n":"RICKY DALBY","a":1,"c":false,"lm":false},{"id":2539,"n":"SCOTT MAWER","a":1,"c":false,"lm":false},{"id":2465,"n":"SHANE COOKE","a":1,"c":false,"lm":false},{"id":2653,"n":"SIMON MURTON","a":1,"c":false,"lm":false}]}