{"name":"Most Goals in a Game - Junior","headers":{"c1":"Name","c2":"Goals"},"info":"From all Junior Games (Minor Round + Finals) from 2007 to 2025. [Minimum 5 Goals]","data":[{"id":2834,"n":"JOSHUA VANDERMEER","a":"14 (2014)","c":false,"lm":false},{"id":3870,"n":"LACHLAN TASKER","a":"14 (2025)","c":true,"lm":false},{"id":2834,"n":"JOSHUA VANDERMEER","a":"13 (2014)","c":false,"lm":false},{"id":2911,"n":"MATTHEW CAIRE","a":"13 (2015)","c":true,"lm":false},{"id":3091,"n":"CAMPBELL WRIGHT","a":"12 (2011)","c":false,"lm":false},{"id":2514,"n":"JAMES CRESSHULL","a":"12 (2007)","c":false,"lm":false},{"id":3091,"n":"CAMPBELL WRIGHT","a":"11 (2010)","c":false,"lm":false},{"id":2885,"n":"DANIEL NASH","a":"11 (2013)","c":true,"lm":false},{"id":2735,"n":"HARRISON GEBHARDT","a":"11 (2008)","c":false,"lm":false},{"id":2735,"n":"HARRISON GEBHARDT","a":"11 (2009)","c":false,"lm":false},{"id":3187,"n":"HARRISON LEMMEY","a":"11 (2017)","c":false,"lm":false},{"id":3618,"n":"LACHLAN SORELLA","a":"11 (2021)","c":false,"lm":false},{"id":3618,"n":"LACHLAN SORELLA","a":"11 (2021)","c":false,"lm":false},{"id":2965,"n":"TOBY SUMMERVILLE","a":"11 (2014)","c":false,"lm":false},{"id":2917,"n":"ADAM  FITZPATRICK","a":"10 (2012)","c":false,"lm":false},{"id":3250,"n":"ADAM BUNWORTH","a":"10 (2019)","c":true,"lm":false},{"id":3241,"n":"BROOKE KLEINIG","a":"10 (2019)","c":false,"lm":false},{"id":3091,"n":"CAMPBELL WRIGHT","a":"10 (2010)","c":false,"lm":false},{"id":2885,"n":"DANIEL NASH","a":"10 (2013)","c":true,"lm":false},{"id":4082,"n":"JAKE SLATTERY","a":"10 (2023)","c":true,"lm":false},{"id":2834,"n":"JOSHUA VANDERMEER","a":"10 (2014)","c":false,"lm":false},{"id":3618,"n":"LACHLAN SORELLA","a":"10 (2021)","c":false,"lm":false},{"id":3618,"n":"LACHLAN SORELLA","a":"10 (2021)","c":false,"lm":false},{"id":4606,"n":"LINCOLN PASTRO","a":"10 (2025)","c":true,"lm":false},{"id":2798,"n":"LUKE ABBOTT","a":"10 (2010)","c":false,"lm":false},{"id":3458,"n":"MARK HOLLIS","a":"10 (2012)","c":false,"lm":false},{"id":3142,"n":"RHYS GALLIFORD","a":"10 (2017)","c":false,"lm":false},{"id":2613,"n":"SAMUEL SMITH","a":"10 (2008)","c":false,"lm":true},{"id":3044,"n":"ALEX BUERSCH","a":"9 (2015)","c":true,"lm":false},{"id":2885,"n":"DANIEL NASH","a":"9 (2015)","c":true,"lm":false},{"id":3033,"n":"D'ARCY MITCHELL","a":"9 (2013)","c":true,"lm":false},{"id":3187,"n":"HARRISON LEMMEY","a":"9 (2017)","c":false,"lm":false},{"id":3877,"n":"JASON GOSS","a":"9 (2015)","c":false,"lm":false},{"id":2834,"n":"JOSHUA VANDERMEER","a":"9 (2013)","c":false,"lm":false},{"id":2927,"n":"LIAM O'BRIEN","a":"9 (2011)","c":false,"lm":false},{"id":4606,"n":"LINCOLN PASTRO","a":"9 (2025)","c":true,"lm":false},{"id":2798,"n":"LUKE ABBOTT","a":"9 (2010)","c":false,"lm":false},{"id":2911,"n":"MATTHEW CAIRE","a":"9 (2015)","c":true,"lm":false},{"id":2911,"n":"MATTHEW CAIRE","a":"9 (2015)","c":true,"lm":false},{"id":3402,"n":"RYAN WILLIAMS","a":"9 (2014)","c":false,"lm":false},{"id":2616,"n":"ADAM STONE","a":"8 (2007)","c":false,"lm":false},{"id":3081,"n":"COOPER GILBERT","a":"8 (2016)","c":false,"lm":false},{"id":2885,"n":"DANIEL NASH","a":"8 (2013)","c":true,"lm":false},{"id":2885,"n":"DANIEL NASH","a":"8 (2015)","c":true,"lm":false},{"id":2735,"n":"HARRISON GEBHARDT","a":"8 (2010)","c":false,"lm":false},{"id":2783,"n":"JACK MITTIGA","a":"8 (2009)","c":false,"lm":false},{"id":2783,"n":"JACK MITTIGA","a":"8 (2009)","c":false,"lm":false},{"id":3093,"n":"JAKE BUNWORTH","a":"8 (2016)","c":true,"lm":false},{"id":2834,"n":"JOSHUA VANDERMEER","a":"8 (2013)","c":false,"lm":false},{"id":2834,"n":"JOSHUA VANDERMEER","a":"8 (2014)","c":false,"lm":false},{"id":2834,"n":"JOSHUA VANDERMEER","a":"8 (2014)","c":false,"lm":false},{"id":3232,"n":"KOBE VANZETTA","a":"8 (2017)","c":false,"lm":false},{"id":3870,"n":"LACHLAN TASKER","a":"8 (2025)","c":true,"lm":false},{"id":4606,"n":"LINCOLN PASTRO","a":"8 (2025)","c":true,"lm":false},{"id":4606,"n":"LINCOLN PASTRO","a":"8 (2025)","c":true,"lm":false},{"id":2798,"n":"LUKE ABBOTT","a":"8 (2009)","c":false,"lm":false},{"id":2911,"n":"MATTHEW CAIRE","a":"8 (2015)","c":true,"lm":false},{"id":2929,"n":"MATTHEW PERROTTA","a":"8 (2013)","c":true,"lm":false},{"id":2613,"n":"SAMUEL SMITH","a":"8 (2007)","c":false,"lm":true},{"id":3766,"n":"SIENNA ALDRIDGE","a":"8 (2022)","c":true,"lm":false},{"id":3045,"n":"TAINE  MITCHELL","a":"8 (2019)","c":false,"lm":false},{"id":2965,"n":"TOBY SUMMERVILLE","a":"8 (2014)","c":false,"lm":false},{"id":2965,"n":"TOBY SUMMERVILLE","a":"8 (2014)","c":false,"lm":false},{"id":3860,"n":"YAW ANTWI","a":"8 (2021)","c":false,"lm":false},{"id":2917,"n":"ADAM  FITZPATRICK","a":"7 (2012)","c":false,"lm":false},{"id":3178,"n":"BLAKE ALDRIDGE","a":"7 (2021)","c":true,"lm":false},{"id":3241,"n":"BROOKE KLEINIG","a":"7 (2018)","c":false,"lm":false},{"id":3241,"n":"BROOKE KLEINIG","a":"7 (2018)","c":false,"lm":false},{"id":2985,"n":"CALEB  HOOPER","a":"7 (2012)","c":false,"lm":false},{"id":3833,"n":"CAMERON BROWN","a":"7 (2024)","c":true,"lm":false},{"id":3091,"n":"CAMPBELL WRIGHT","a":"7 (2011)","c":false,"lm":false},{"id":3834,"n":"COBY HIBBERT","a":"7 (2022)","c":true,"lm":false},{"id":2708,"n":"DECLAN WHITE","a":"7 (2009)","c":false,"lm":false},{"id":3563,"n":"ETHAN MILLEN","a":"7 (2014)","c":false,"lm":false},{"id":2735,"n":"HARRISON GEBHARDT","a":"7 (2010)","c":false,"lm":false},{"id":2735,"n":"HARRISON GEBHARDT","a":"7 (2011)","c":false,"lm":false},{"id":2735,"n":"HARRISON GEBHARDT","a":"7 (2012)","c":false,"lm":false},{"id":3187,"n":"HARRISON LEMMEY","a":"7 (2017)","c":false,"lm":false},{"id":2783,"n":"JACK MITTIGA","a":"7 (2009)","c":false,"lm":false},{"id":2783,"n":"JACK MITTIGA","a":"7 (2009)","c":false,"lm":false},{"id":2783,"n":"JACK MITTIGA","a":"7 (2011)","c":false,"lm":false},{"id":2783,"n":"JACK MITTIGA","a":"7 (2011)","c":false,"lm":false},{"id":3231,"n":"JACKSON ROBERTS","a":"7 (2016)","c":false,"lm":false},{"id":3247,"n":"JAMES HACKETT","a":"7 (2016)","c":true,"lm":false},{"id":3877,"n":"JASON GOSS","a":"7 (2015)","c":false,"lm":false},{"id":3823,"n":"JAY SCANLAN","a":"7 (2022)","c":false,"lm":false},{"id":4272,"n":"JOSHUA LEES","a":"7 (2023)","c":true,"lm":false},{"id":4272,"n":"JOSHUA LEES","a":"7 (2023)","c":true,"lm":false},{"id":2834,"n":"JOSHUA VANDERMEER","a":"7 (2013)","c":false,"lm":false},{"id":2907,"n":"LACHLAN BATES","a":"7 (2013)","c":false,"lm":false},{"id":3618,"n":"LACHLAN SORELLA","a":"7 (2020)","c":false,"lm":false},{"id":3618,"n":"LACHLAN SORELLA","a":"7 (2021)","c":false,"lm":false},{"id":2798,"n":"LUKE ABBOTT","a":"7 (2008)","c":false,"lm":false},{"id":2798,"n":"LUKE ABBOTT","a":"7 (2008)","c":false,"lm":false},{"id":3458,"n":"MARK HOLLIS","a":"7 (2012)","c":false,"lm":false},{"id":2911,"n":"MATTHEW CAIRE","a":"7 (2014)","c":true,"lm":false},{"id":3841,"n":"MATTHEW REED","a":"7 (2015)","c":false,"lm":false},{"id":3841,"n":"MATTHEW REED","a":"7 (2015)","c":false,"lm":false},{"id":2858,"n":"NATHAN LAITY","a":"7 (2014)","c":false,"lm":false},{"id":3251,"n":"NICHOLAS MAGOR","a":"7 (2013)","c":false,"lm":false},{"id":3251,"n":"NICHOLAS MAGOR","a":"7 (2013)","c":false,"lm":false},{"id":3142,"n":"RHYS GALLIFORD","a":"7 (2018)","c":false,"lm":false},{"id":3142,"n":"RHYS GALLIFORD","a":"7 (2018)","c":false,"lm":false},{"id":2613,"n":"SAMUEL SMITH","a":"7 (2008)","c":false,"lm":true},{"id":2847,"n":"SHANE HEATLEY","a":"7 (2010)","c":false,"lm":false},{"id":2965,"n":"TOBY SUMMERVILLE","a":"7 (2014)","c":false,"lm":false},{"id":2965,"n":"TOBY SUMMERVILLE","a":"7 (2016)","c":false,"lm":false},{"id":2917,"n":"ADAM  FITZPATRICK","a":"6 (2012)","c":false,"lm":false},{"id":3854,"n":"ALI BALTAGIE","a":"6 (2015)","c":true,"lm":false},{"id":2935,"n":"BEN PAPPS","a":"6 (2009)","c":false,"lm":false},{"id":2684,"n":"BLAKE HORROCKS","a":"6 (2007)","c":false,"lm":false},{"id":4005,"n":"BLUE PEARSE","a":"6 (2018)","c":false,"lm":false},{"id":2870,"n":"BRADLEY CLARK","a":"6 (2013)","c":false,"lm":false},{"id":3119,"n":"BRADLEY PATTERSON","a":"6 (2014)","c":true,"lm":false},{"id":2932,"n":"BRAYDEN ROBERTS","a":"6 (2014)","c":false,"lm":false},{"id":2786,"n":"BRENDAN HILLIER","a":"6 (2008)","c":false,"lm":false},{"id":3241,"n":"BROOKE KLEINIG","a":"6 (2019)","c":false,"lm":false},{"id":3241,"n":"BROOKE KLEINIG","a":"6 (2019)","c":false,"lm":false},{"id":2667,"n":"CALLUM ADAMS","a":"6 (2009)","c":false,"lm":false},{"id":3833,"n":"CAMERON BROWN","a":"6 (2025)","c":true,"lm":false},{"id":3833,"n":"CAMERON BROWN","a":"6 (2025)","c":true,"lm":false},{"id":3091,"n":"CAMPBELL WRIGHT","a":"6 (2010)","c":false,"lm":false},{"id":3091,"n":"CAMPBELL WRIGHT","a":"6 (2010)","c":false,"lm":false},{"id":3091,"n":"CAMPBELL WRIGHT","a":"6 (2011)","c":false,"lm":false},{"id":3091,"n":"CAMPBELL WRIGHT","a":"6 (2012)","c":false,"lm":false},{"id":3091,"n":"CAMPBELL WRIGHT","a":"6 (2014)","c":false,"lm":false},{"id":4313,"n":"CASCIA SMAILES","a":"6 (2022)","c":false,"lm":false},{"id":4313,"n":"CASCIA SMAILES","a":"6 (2022)","c":false,"lm":false},{"id":4118,"n":"CHARLIE ROBERTS","a":"6 (2024)","c":true,"lm":false},{"id":3834,"n":"COBY HIBBERT","a":"6 (2022)","c":true,"lm":false},{"id":3081,"n":"COOPER GILBERT","a":"6 (2016)","c":false,"lm":false},{"id":3914,"n":"CORY SAWYER","a":"6 (2015)","c":false,"lm":false},{"id":2656,"n":"CRAIG PETERSEN","a":"6 (2009)","c":false,"lm":false},{"id":2885,"n":"DANIEL NASH","a":"6 (2013)","c":true,"lm":false},{"id":2885,"n":"DANIEL NASH","a":"6 (2015)","c":true,"lm":false},{"id":2885,"n":"DANIEL NASH","a":"6 (2015)","c":true,"lm":false},{"id":2708,"n":"DECLAN WHITE","a":"6 (2008)","c":false,"lm":false},{"id":2708,"n":"DECLAN WHITE","a":"6 (2009)","c":false,"lm":false},{"id":4100,"n":"ETHAN JOHNSON","a":"6 (2022)","c":true,"lm":false},{"id":3563,"n":"ETHAN MILLEN","a":"6 (2016)","c":false,"lm":false},{"id":3563,"n":"ETHAN MILLEN","a":"6 (2016)","c":false,"lm":false},{"id":4157,"n":"HARRISON COONEY","a":"6 (2024)","c":true,"lm":false},{"id":2735,"n":"HARRISON GEBHARDT","a":"6 (2010)","c":false,"lm":false},{"id":2735,"n":"HARRISON GEBHARDT","a":"6 (2011)","c":false,"lm":false},{"id":2735,"n":"HARRISON GEBHARDT","a":"6 (2011)","c":false,"lm":false},{"id":2735,"n":"HARRISON GEBHARDT","a":"6 (2012)","c":false,"lm":false},{"id":2735,"n":"HARRISON GEBHARDT","a":"6 (2012)","c":false,"lm":false},{"id":2735,"n":"HARRISON GEBHARDT","a":"6 (2012)","c":false,"lm":false},{"id":2735,"n":"HARRISON GEBHARDT","a":"6 (2012)","c":false,"lm":false},{"id":4223,"n":"INDIANNA ROBERTS","a":"6 (2018)","c":false,"lm":false},{"id":4299,"n":"ISABEL CROWTHER","a":"6 (2021)","c":false,"lm":false},{"id":4416,"n":"JACK CHAPLIN","a":"6 (2023)","c":true,"lm":false},{"id":2783,"n":"JACK MITTIGA","a":"6 (2009)","c":false,"lm":false},{"id":2783,"n":"JACK MITTIGA","a":"6 (2009)","c":false,"lm":false},{"id":2783,"n":"JACK MITTIGA","a":"6 (2011)","c":false,"lm":false},{"id":2783,"n":"JACK MITTIGA","a":"6 (2013)","c":false,"lm":false},{"id":2514,"n":"JAMES CRESSHULL","a":"6 (2007)","c":false,"lm":false},{"id":2514,"n":"JAMES CRESSHULL","a":"6 (2007)","c":false,"lm":false},{"id":4388,"n":"JORDAN MOREHOUSE","a":"6 (2022)","c":false,"lm":false},{"id":3411,"n":"JORDAN SELLAR","a":"6 (2014)","c":false,"lm":false},{"id":2834,"n":"JOSHUA VANDERMEER","a":"6 (2014)","c":false,"lm":false},{"id":2834,"n":"JOSHUA VANDERMEER","a":"6 (2014)","c":false,"lm":false},{"id":4201,"n":"KADE HATTON","a":"6 (2025)","c":true,"lm":false},{"id":4201,"n":"KADE HATTON","a":"6 (2025)","c":true,"lm":false},{"id":4022,"n":"KRISTIAN CIABATTONI","a":"6 (2017)","c":false,"lm":false},{"id":2907,"n":"LACHLAN BATES","a":"6 (2011)","c":false,"lm":false},{"id":2907,"n":"LACHLAN BATES","a":"6 (2011)","c":false,"lm":false},{"id":2907,"n":"LACHLAN BATES","a":"6 (2013)","c":false,"lm":false},{"id":2907,"n":"LACHLAN BATES","a":"6 (2013)","c":false,"lm":false},{"id":3443,"n":"LACHLAN ROBERTS","a":"6 (2018)","c":false,"lm":false},{"id":3618,"n":"LACHLAN SORELLA","a":"6 (2018)","c":false,"lm":false},{"id":3618,"n":"LACHLAN SORELLA","a":"6 (2019)","c":false,"lm":false},{"id":3618,"n":"LACHLAN SORELLA","a":"6 (2020)","c":false,"lm":false},{"id":3618,"n":"LACHLAN SORELLA","a":"6 (2021)","c":false,"lm":false},{"id":3618,"n":"LACHLAN SORELLA","a":"6 (2021)","c":false,"lm":false},{"id":4066,"n":"LEITH (JNR) MITCHELL","a":"6 (2019)","c":false,"lm":false},{"id":4606,"n":"LINCOLN PASTRO","a":"6 (2025)","c":true,"lm":false},{"id":4606,"n":"LINCOLN PASTRO","a":"6 (2025)","c":true,"lm":false},{"id":2798,"n":"LUKE ABBOTT","a":"6 (2009)","c":false,"lm":false},{"id":2798,"n":"LUKE ABBOTT","a":"6 (2010)","c":false,"lm":false},{"id":3037,"n":"MACKENZIE SHORT","a":"6 (2015)","c":true,"lm":false},{"id":2911,"n":"MATTHEW CAIRE","a":"6 (2011)","c":true,"lm":false},{"id":2911,"n":"MATTHEW CAIRE","a":"6 (2014)","c":true,"lm":false},{"id":2911,"n":"MATTHEW CAIRE","a":"6 (2015)","c":true,"lm":false},{"id":2911,"n":"MATTHEW CAIRE","a":"6 (2015)","c":true,"lm":false},{"id":2929,"n":"MATTHEW PERROTTA","a":"6 (2013)","c":true,"lm":false},{"id":2929,"n":"MATTHEW PERROTTA","a":"6 (2013)","c":true,"lm":false},{"id":3841,"n":"MATTHEW REED","a":"6 (2015)","c":false,"lm":false},{"id":3853,"n":"NATHAN ROHRLACH","a":"6 (2015)","c":false,"lm":false},{"id":4590,"n":"NEIVE MORGAN","a":"6 (2024)","c":true,"lm":false},{"id":3386,"n":"NELSON WILLIAMS","a":"6 (2015)","c":false,"lm":false},{"id":3386,"n":"NELSON WILLIAMS","a":"6 (2015)","c":false,"lm":false},{"id":3251,"n":"NICHOLAS MAGOR","a":"6 (2013)","c":false,"lm":false},{"id":4543,"n":"OLIVER FIRGAIRA","a":"6 (2025)","c":true,"lm":false},{"id":3142,"n":"RHYS GALLIFORD","a":"6 (2018)","c":false,"lm":false},{"id":3142,"n":"RHYS GALLIFORD","a":"6 (2018)","c":false,"lm":false},{"id":3142,"n":"RHYS GALLIFORD","a":"6 (2019)","c":false,"lm":false},{"id":3142,"n":"RHYS GALLIFORD","a":"6 (2020)","c":false,"lm":false},{"id":3140,"n":"RICHARD WILSON","a":"6 (2010)","c":false,"lm":false},{"id":3099,"n":"RYAN MOUNTFORD","a":"6 (2013)","c":true,"lm":false},{"id":3099,"n":"RYAN MOUNTFORD","a":"6 (2015)","c":true,"lm":false},{"id":3402,"n":"RYAN WILLIAMS","a":"6 (2016)","c":false,"lm":false},{"id":2827,"n":"SAMUEL HIOSAN","a":"6 (2013)","c":false,"lm":false},{"id":2613,"n":"SAMUEL SMITH","a":"6 (2007)","c":false,"lm":true},{"id":2613,"n":"SAMUEL SMITH","a":"6 (2008)","c":false,"lm":true},{"id":2613,"n":"SAMUEL SMITH","a":"6 (2008)","c":false,"lm":true},{"id":3045,"n":"TAINE  MITCHELL","a":"6 (2015)","c":false,"lm":false},{"id":3369,"n":"THOMAS VAN JAARSVELDT","a":"6 (2021)","c":false,"lm":false},{"id":4466,"n":"TIANA LUSH","a":"6 (2022)","c":true,"lm":false},{"id":2965,"n":"TOBY SUMMERVILLE","a":"6 (2014)","c":false,"lm":false},{"id":2965,"n":"TOBY SUMMERVILLE","a":"6 (2014)","c":false,"lm":false},{"id":2965,"n":"TOBY SUMMERVILLE","a":"6 (2015)","c":false,"lm":false},{"id":2918,"n":"TRENT FORESTER","a":"6 (2011)","c":false,"lm":false},{"id":2917,"n":"ADAM  FITZPATRICK","a":"5 (2012)","c":false,"lm":false},{"id":2820,"n":"ADAM COLES","a":"5 (2012)","c":false,"lm":false},{"id":4348,"n":"AIDEN GRAYSON","a":"5 (2021)","c":true,"lm":false},{"id":3854,"n":"ALI BALTAGIE","a":"5 (2017)","c":true,"lm":false},{"id":4306,"n":"ASHLIE CLANCEY","a":"5 (2020)","c":false,"lm":false},{"id":2835,"n":"BEAU WAKELY","a":"5 (2014)","c":false,"lm":false},{"id":2935,"n":"BEN PAPPS","a":"5 (2009)","c":false,"lm":false},{"id":2935,"n":"BEN PAPPS","a":"5 (2010)","c":false,"lm":false},{"id":2935,"n":"BEN PAPPS","a":"5 (2011)","c":false,"lm":false},{"id":2698,"n":"BENJAMIN  SCOTT","a":"5 (2007)","c":false,"lm":false},{"id":2780,"n":"BLAISE TOMKINS","a":"5 (2010)","c":true,"lm":true},{"id":3178,"n":"BLAKE ALDRIDGE","a":"5 (2017)","c":true,"lm":false},{"id":2674,"n":"BRADLEY CRADDOCK","a":"5 (2007)","c":false,"lm":false},{"id":2674,"n":"BRADLEY CRADDOCK","a":"5 (2008)","c":false,"lm":false},{"id":2833,"n":"BRETT TURNER","a":"5 (2010)","c":false,"lm":false},{"id":3241,"n":"BROOKE KLEINIG","a":"5 (2019)","c":false,"lm":false},{"id":3241,"n":"BROOKE KLEINIG","a":"5 (2019)","c":false,"lm":false},{"id":3241,"n":"BROOKE KLEINIG","a":"5 (2019)","c":false,"lm":false},{"id":4491,"n":"CALLUM ATHEY","a":"5 (2023)","c":false,"lm":false},{"id":4491,"n":"CALLUM ATHEY","a":"5 (2023)","c":false,"lm":false},{"id":2906,"n":"CAMERON BAHNISCH","a":"5 (2013)","c":false,"lm":false},{"id":3910,"n":"CAMERON STEWART","a":"5 (2016)","c":false,"lm":false},{"id":3091,"n":"CAMPBELL WRIGHT","a":"5 (2010)","c":false,"lm":false},{"id":3091,"n":"CAMPBELL WRIGHT","a":"5 (2013)","c":false,"lm":false},{"id":4313,"n":"CASCIA SMAILES","a":"5 (2020)","c":false,"lm":false},{"id":4118,"n":"CHARLIE ROBERTS","a":"5 (2024)","c":true,"lm":false},{"id":3042,"n":"CHRISTOPHER BUERSCH","a":"5 (2017)","c":false,"lm":false},{"id":4077,"n":"CLAYTON PUDNEY","a":"5 (2018)","c":false,"lm":false},{"id":3834,"n":"COBY HIBBERT","a":"5 (2022)","c":true,"lm":false},{"id":3081,"n":"COOPER GILBERT","a":"5 (2016)","c":false,"lm":false},{"id":3081,"n":"COOPER GILBERT","a":"5 (2017)","c":false,"lm":false},{"id":3081,"n":"COOPER GILBERT","a":"5 (2017)","c":false,"lm":false},{"id":4203,"n":"COOPER SLATTERY","a":"5 (2024)","c":true,"lm":false},{"id":2656,"n":"CRAIG PETERSEN","a":"5 (2008)","c":false,"lm":false},{"id":2885,"n":"DANIEL NASH","a":"5 (2013)","c":true,"lm":false},{"id":2885,"n":"DANIEL NASH","a":"5 (2013)","c":true,"lm":false},{"id":2885,"n":"DANIEL NASH","a":"5 (2015)","c":true,"lm":false},{"id":3986,"n":"DECLAN HENTY-SMITH","a":"5 (2016)","c":false,"lm":false},{"id":4149,"n":"DECLAN STONE","a":"5 (2024)","c":true,"lm":false},{"id":2934,"n":"DECLAN TOMKINS","a":"5 (2011)","c":true,"lm":false},{"id":2934,"n":"DECLAN TOMKINS","a":"5 (2012)","c":true,"lm":false},{"id":2934,"n":"DECLAN TOMKINS","a":"5 (2012)","c":true,"lm":false},{"id":3021,"n":"ELLIOTT MODRA","a":"5 (2011)","c":false,"lm":false},{"id":4571,"n":"EMILY KELLY","a":"5 (2025)","c":true,"lm":false},{"id":3563,"n":"ETHAN MILLEN","a":"5 (2014)","c":false,"lm":false},{"id":3563,"n":"ETHAN MILLEN","a":"5 (2016)","c":false,"lm":false},{"id":3406,"n":"ETHAN WILDMAN","a":"5 (2015)","c":true,"lm":false},{"id":4157,"n":"HARRISON COONEY","a":"5 (2024)","c":true,"lm":false},{"id":2735,"n":"HARRISON GEBHARDT","a":"5 (2007)","c":false,"lm":false},{"id":2735,"n":"HARRISON GEBHARDT","a":"5 (2008)","c":false,"lm":false},{"id":2735,"n":"HARRISON GEBHARDT","a":"5 (2008)","c":false,"lm":false},{"id":2735,"n":"HARRISON GEBHARDT","a":"5 (2008)","c":false,"lm":false},{"id":2735,"n":"HARRISON GEBHARDT","a":"5 (2010)","c":false,"lm":false},{"id":2735,"n":"HARRISON GEBHARDT","a":"5 (2010)","c":false,"lm":false},{"id":2735,"n":"HARRISON GEBHARDT","a":"5 (2010)","c":false,"lm":false},{"id":2735,"n":"HARRISON GEBHARDT","a":"5 (2011)","c":false,"lm":false},{"id":2735,"n":"HARRISON GEBHARDT","a":"5 (2012)","c":false,"lm":false},{"id":3187,"n":"HARRISON LEMMEY","a":"5 (2017)","c":false,"lm":false},{"id":3187,"n":"HARRISON LEMMEY","a":"5 (2019)","c":false,"lm":false},{"id":3187,"n":"HARRISON LEMMEY","a":"5 (2019)","c":false,"lm":false},{"id":3187,"n":"HARRISON LEMMEY","a":"5 (2019)","c":false,"lm":false},{"id":3570,"n":"HUGH NASH","a":"5 (2019)","c":true,"lm":false},{"id":4299,"n":"ISABEL CROWTHER","a":"5 (2021)","c":false,"lm":false},{"id":4416,"n":"JACK CHAPLIN","a":"5 (2023)","c":true,"lm":false},{"id":2783,"n":"JACK MITTIGA","a":"5 (2008)","c":false,"lm":false},{"id":2783,"n":"JACK MITTIGA","a":"5 (2008)","c":false,"lm":false},{"id":2783,"n":"JACK MITTIGA","a":"5 (2009)","c":false,"lm":false},{"id":2783,"n":"JACK MITTIGA","a":"5 (2009)","c":false,"lm":false},{"id":2783,"n":"JACK MITTIGA","a":"5 (2009)","c":false,"lm":false},{"id":2783,"n":"JACK MITTIGA","a":"5 (2009)","c":false,"lm":false},{"id":2783,"n":"JACK MITTIGA","a":"5 (2011)","c":false,"lm":false},{"id":2783,"n":"JACK MITTIGA","a":"5 (2011)","c":false,"lm":false},{"id":2783,"n":"JACK MITTIGA","a":"5 (2012)","c":false,"lm":false},{"id":3231,"n":"JACKSON ROBERTS","a":"5 (2016)","c":false,"lm":false},{"id":3231,"n":"JACKSON ROBERTS","a":"5 (2016)","c":false,"lm":false},{"id":3685,"n":"JACKSON WILLIAMS","a":"5 (2020)","c":false,"lm":false},{"id":4208,"n":"JACOB COMLEY","a":"5 (2018)","c":false,"lm":false},{"id":4082,"n":"JAKE SLATTERY","a":"5 (2023)","c":true,"lm":false},{"id":3989,"n":"JALEN PRYOR","a":"5 (2017)","c":false,"lm":false},{"id":2514,"n":"JAMES CRESSHULL","a":"5 (2007)","c":false,"lm":false},{"id":3866,"n":"JAMES LANGDON","a":"5 (2025)","c":true,"lm":false},{"id":3866,"n":"JAMES LANGDON","a":"5 (2025)","c":true,"lm":false},{"id":3877,"n":"JASON GOSS","a":"5 (2015)","c":false,"lm":false},{"id":3877,"n":"JASON GOSS","a":"5 (2017)","c":false,"lm":false},{"id":3877,"n":"JASON GOSS","a":"5 (2017)","c":false,"lm":false},{"id":2779,"n":"JESS LEMON","a":"5 (2008)","c":false,"lm":false},{"id":4388,"n":"JORDAN MOREHOUSE","a":"5 (2021)","c":false,"lm":false},{"id":4388,"n":"JORDAN MOREHOUSE","a":"5 (2022)","c":false,"lm":false},{"id":4388,"n":"JORDAN MOREHOUSE","a":"5 (2022)","c":false,"lm":false},{"id":3411,"n":"JORDAN SELLAR","a":"5 (2012)","c":false,"lm":false},{"id":3223,"n":"JOSHUA HEADING","a":"5 (2015)","c":false,"lm":false},{"id":4272,"n":"JOSHUA LEES","a":"5 (2023)","c":true,"lm":false},{"id":2834,"n":"JOSHUA VANDERMEER","a":"5 (2013)","c":false,"lm":false},{"id":2834,"n":"JOSHUA VANDERMEER","a":"5 (2013)","c":false,"lm":false},{"id":2834,"n":"JOSHUA VANDERMEER","a":"5 (2014)","c":false,"lm":false},{"id":4201,"n":"KADE HATTON","a":"5 (2024)","c":true,"lm":false},{"id":3232,"n":"KOBE VANZETTA","a":"5 (2019)","c":false,"lm":false},{"id":2657,"n":"KYLE PETTY","a":"5 (2008)","c":false,"lm":false},{"id":2657,"n":"KYLE PETTY","a":"5 (2009)","c":false,"lm":false},{"id":2907,"n":"LACHLAN BATES","a":"5 (2013)","c":false,"lm":false},{"id":2907,"n":"LACHLAN BATES","a":"5 (2013)","c":false,"lm":false},{"id":2907,"n":"LACHLAN BATES","a":"5 (2014)","c":false,"lm":false},{"id":3443,"n":"LACHLAN ROBERTS","a":"5 (2019)","c":false,"lm":false},{"id":3443,"n":"LACHLAN ROBERTS","a":"5 (2020)","c":false,"lm":false},{"id":3618,"n":"LACHLAN SORELLA","a":"5 (2018)","c":false,"lm":false},{"id":3618,"n":"LACHLAN SORELLA","a":"5 (2021)","c":false,"lm":false},{"id":3618,"n":"LACHLAN SORELLA","a":"5 (2021)","c":false,"lm":false},{"id":3618,"n":"LACHLAN SORELLA","a":"5 (2021)","c":false,"lm":false},{"id":4066,"n":"LEITH (JNR) MITCHELL","a":"5 (2019)","c":false,"lm":false},{"id":4606,"n":"LINCOLN PASTRO","a":"5 (2025)","c":true,"lm":false},{"id":4606,"n":"LINCOLN PASTRO","a":"5 (2025)","c":true,"lm":false},{"id":3037,"n":"MACKENZIE SHORT","a":"5 (2014)","c":true,"lm":false},{"id":3037,"n":"MACKENZIE SHORT","a":"5 (2015)","c":true,"lm":false},{"id":4094,"n":"MACKLIN BROOK","a":"5 (2025)","c":true,"lm":false},{"id":3458,"n":"MARK HOLLIS","a":"5 (2012)","c":false,"lm":false},{"id":2911,"n":"MATTHEW CAIRE","a":"5 (2012)","c":true,"lm":false},{"id":2911,"n":"MATTHEW CAIRE","a":"5 (2013)","c":true,"lm":false},{"id":2911,"n":"MATTHEW CAIRE","a":"5 (2013)","c":true,"lm":false},{"id":2911,"n":"MATTHEW CAIRE","a":"5 (2015)","c":true,"lm":false},{"id":2953,"n":"MATTHEW HUNTER","a":"5 (2012)","c":false,"lm":false},{"id":2953,"n":"MATTHEW HUNTER","a":"5 (2015)","c":false,"lm":false},{"id":3334,"n":"MATTHEW PEARCE","a":"5 (2019)","c":false,"lm":false},{"id":3334,"n":"MATTHEW PEARCE","a":"5 (2020)","c":false,"lm":false},{"id":3334,"n":"MATTHEW PEARCE","a":"5 (2021)","c":false,"lm":false},{"id":2861,"n":"MATTHEW PHILLIPS","a":"5 (2014)","c":false,"lm":false},{"id":3841,"n":"MATTHEW REED","a":"5 (2015)","c":false,"lm":false},{"id":3988,"n":"MAX CLIFTON","a":"5 (2017)","c":false,"lm":false},{"id":4579,"n":"MAX KELLY","a":"5 (2025)","c":true,"lm":false},{"id":2867,"n":"NATHAN BEENHAM","a":"5 (2015)","c":true,"lm":false},{"id":2867,"n":"NATHAN BEENHAM","a":"5 (2016)","c":true,"lm":false},{"id":2852,"n":"NATHAN CLARIDGE","a":"5 (2014)","c":false,"lm":false},{"id":2858,"n":"NATHAN LAITY","a":"5 (2014)","c":false,"lm":false},{"id":2858,"n":"NATHAN LAITY","a":"5 (2014)","c":false,"lm":false},{"id":3853,"n":"NATHAN ROHRLACH","a":"5 (2015)","c":false,"lm":false},{"id":3386,"n":"NELSON WILLIAMS","a":"5 (2015)","c":false,"lm":false},{"id":3386,"n":"NELSON WILLIAMS","a":"5 (2015)","c":false,"lm":false},{"id":3386,"n":"NELSON WILLIAMS","a":"5 (2015)","c":false,"lm":false},{"id":3386,"n":"NELSON WILLIAMS","a":"5 (2015)","c":false,"lm":false},{"id":3251,"n":"NICHOLAS MAGOR","a":"5 (2011)","c":false,"lm":false},{"id":3251,"n":"NICHOLAS MAGOR","a":"5 (2012)","c":false,"lm":false},{"id":4084,"n":"OWEN HIBBERT","a":"5 (2023)","c":true,"lm":false},{"id":3067,"n":"PATRICK SPERLING","a":"5 (2011)","c":false,"lm":false},{"id":3142,"n":"RHYS GALLIFORD","a":"5 (2017)","c":false,"lm":false},{"id":3142,"n":"RHYS GALLIFORD","a":"5 (2017)","c":false,"lm":false},{"id":3142,"n":"RHYS GALLIFORD","a":"5 (2017)","c":false,"lm":false},{"id":3142,"n":"RHYS GALLIFORD","a":"5 (2018)","c":false,"lm":false},{"id":3142,"n":"RHYS GALLIFORD","a":"5 (2019)","c":false,"lm":false},{"id":3451,"n":"RILEY STONE","a":"5 (2019)","c":true,"lm":false},{"id":3099,"n":"RYAN MOUNTFORD","a":"5 (2015)","c":true,"lm":false},{"id":3099,"n":"RYAN MOUNTFORD","a":"5 (2015)","c":true,"lm":false},{"id":3099,"n":"RYAN MOUNTFORD","a":"5 (2016)","c":true,"lm":false},{"id":3402,"n":"RYAN WILLIAMS","a":"5 (2014)","c":false,"lm":false},{"id":3867,"n":"SALEH BALTAGIE","a":"5 (2021)","c":true,"lm":false},{"id":3380,"n":"SAMUEL BURBRIDGE","a":"5 (2021)","c":false,"lm":false},{"id":2729,"n":"SAMUEL NAPIER","a":"5 (2009)","c":false,"lm":false},{"id":2613,"n":"SAMUEL SMITH","a":"5 (2007)","c":false,"lm":true},{"id":2613,"n":"SAMUEL SMITH","a":"5 (2007)","c":false,"lm":true},{"id":2613,"n":"SAMUEL SMITH","a":"5 (2008)","c":false,"lm":true},{"id":2613,"n":"SAMUEL SMITH","a":"5 (2008)","c":false,"lm":true},{"id":2613,"n":"SAMUEL SMITH","a":"5 (2008)","c":false,"lm":true},{"id":2613,"n":"SAMUEL SMITH","a":"5 (2008)","c":false,"lm":true},{"id":3426,"n":"SAMUEL THARALDSEN","a":"5 (2012)","c":true,"lm":false},{"id":3427,"n":"SCOTT KUMNICK","a":"5 (2013)","c":false,"lm":false},{"id":3544,"n":"SEBASTIAN GRIFFIN","a":"5 (2015)","c":false,"lm":false},{"id":3766,"n":"SIENNA ALDRIDGE","a":"5 (2022)","c":true,"lm":false},{"id":2838,"n":"THOMAS BREYNARD","a":"5 (2010)","c":false,"lm":false},{"id":3369,"n":"THOMAS VAN JAARSVELDT","a":"5 (2018)","c":false,"lm":false},{"id":3369,"n":"THOMAS VAN JAARSVELDT","a":"5 (2021)","c":false,"lm":false},{"id":2895,"n":"TIM SCOTT","a":"5 (2014)","c":false,"lm":false},{"id":2965,"n":"TOBY SUMMERVILLE","a":"5 (2014)","c":false,"lm":false},{"id":2965,"n":"TOBY SUMMERVILLE","a":"5 (2014)","c":false,"lm":false},{"id":2965,"n":"TOBY SUMMERVILLE","a":"5 (2014)","c":false,"lm":false},{"id":2965,"n":"TOBY SUMMERVILLE","a":"5 (2015)","c":false,"lm":false},{"id":2965,"n":"TOBY SUMMERVILLE","a":"5 (2016)","c":false,"lm":false},{"id":3048,"n":"TYSON DYER","a":"5 (2016)","c":false,"lm":false},{"id":3048,"n":"TYSON DYER","a":"5 (2016)","c":false,"lm":false},{"id":3860,"n":"YAW ANTWI","a":"5 (2021)","c":false,"lm":false}]}