{"firstName":"DARROLL","middleName":"","lastName":"NUTTMAN","agrade":11,"senior":158,"junior":0,"minYear":1981,"maxYear":1995,"seasons":13,"aGradeGoals":0,"seniorGoals":0,"juniorGoals":0,"years":[{"y":"1981","uGames":16},{"y":"1982","uGames":16},{"y":"1983","uGames":16},{"y":"1984","uGames":18},{"y":"1985","uGames":11},{"y":"1986","uGames":18},{"y":"1987","bGames":18},{"y":"1988","bGames":6},{"y":"1989","aGames":3,"bGames":14},{"y":"1990","aGames":7,"bGames":8},{"y":"1991","aGames":1,"bGames":4},{"y":"1992","bGames":1},{"y":"1995","bGames":1},{"y":"Totals","aGames":11,"bGames":52,"uGames":95}]}