{"name":"Avg Goals Per Game - B Grade","headers":{"c1":"Name","c2":"Goals"},"data":[{"n":"DANIEL BUTCHER","a":"5.63"},{"n":"JARROD ALMOND","a":"5.00"},{"n":"MATTHEW RAITT","a":"5.00"},{"n":"ADAM CAREY","a":"4.00"},{"n":"ASHLEY DUDMAN","a":"4.00"},{"n":"ADAM STONE","a":"3.50"},{"n":"HARRISON GEBHARDT","a":"3.41"},{"n":"RICKY DALBY","a":"3.28"},{"n":"SHANE WILLMENT","a":"2.60"},{"n":"MARK HOLLIS","a":"2.46"},{"n":"RYAN MOUNTFORD","a":"2.22"},{"n":"MICHAEL HASLAM","a":"2.15"},{"n":"MATT CAREY","a":"2.00"},{"n":"SIMON MURTON","a":"1.88"},{"n":"BRADLEY PATTERSON","a":"1.86"},{"n":"SAMUEL HIOSAN","a":"1.71"},{"n":"THOMAS SOUTH","a":"1.70"},{"n":"MATTHEW HAGIAS","a":"1.68"},{"n":"CHAD HAMP","a":"1.61"},{"n":"NATHAN MIFSUD","a":"1.57"},{"n":"JUSTIN BAILEY","a":"1.52"},{"n":"JORDAN WAYNE","a":"1.50"},{"n":"JOSHUA VANDERMEER","a":"1.50"},{"n":"JUSTIN RICHARDSON","a":"1.50"},{"n":"LUKE ABBOTT","a":"1.50"},{"n":"THOMAS BREYNARD","a":"1.50"},{"n":"LUKE HILL","a":"1.44"},{"n":"SIMON ZACPAL","a":"1.41"},{"n":"KYLE PETTY","a":"1.40"},{"n":"JERICHO JOHN","a":"1.36"},{"n":"CORY SAWYER","a":"1.35"},{"n":"ANDREW LIVERTON","a":"1.33"},{"n":"BEN PAPPS","a":"1.33"},{"n":"MITCHELL EDWARDS","a":"1.33"},{"n":"CRAIG PETERSEN","a":"1.27"},{"n":"MATTHEW JARVIS","a":"1.25"},{"n":"DECLAN TOMKINS","a":"1.23"},{"n":"MATTHEW CAIRE","a":"1.22"},{"n":"MATTHEW HAMP","a":"1.22"},{"n":"BEN COONEY","a":"1.19"},{"n":"JUSTIN AYRIS","a":"1.19"},{"n":"JACOB NUTTMAN","a":"1.18"},{"n":"PETER MASIKA","a":"1.17"},{"n":"TIM MEINECKE","a":"1.16"},{"n":"DANIEL ZANDONA","a":"1.15"},{"n":"JORDAN SELLAR","a":"1.14"},{"n":"CAMPBELL WRIGHT","a":"1.13"},{"n":"BRADLEY GROWDEN","a":"1.08"},{"n":"JARRAD LEE","a":"1.04"},{"n":"ADAM COLES","a":"1.00"},{"n":"BRADLEY CRADDOCK","a":"1.00"},{"n":"CLINTON FOSTER","a":"1.00"},{"n":"DALE CURTIS","a":"1.00"},{"n":"JACK MITTIGA","a":"1.00"},{"n":"JOSHUA BYERLEE","a":"1.00"},{"n":"KRISTIAN CIABATTONI","a":"1.00"},{"n":"KYM DOOLEY","a":"1.00"},{"n":"LUKE STEWART","a":"1.00"},{"n":"MITCHELL JOHNSON","a":"1.00"},{"n":"NICK COLLINS","a":"1.00"},{"n":"RYAN WILLIAMS","a":"1.00"},{"n":"TRISTAN BALDEY","a":"1.00"},{"n":"KANE ABBOTT","a":"0.98"},{"n":"NICK BAILEY","a":"0.91"},{"n":"CALLUM ADAMS","a":"0.90"},{"n":"CHOL MAJOK","a":"0.89"},{"n":"STEVEN GATER","a":"0.86"},{"n":"CAMERON VAN DEN BOS","a":"0.82"},{"n":"ANDREW MCGEE","a":"0.80"},{"n":"DAVID WALLER","a":"0.80"},{"n":"MATTHEW WRIGHT","a":"0.80"},{"n":"TOM STARKEY","a":"0.78"},{"n":"ELLIOT MODRA","a":"0.75"},{"n":"RICHARD MCNAMARA","a":"0.75"},{"n":"LEIGH O'MALLEY","a":"0.72"},{"n":"BRANT RAMAGE","a":"0.71"},{"n":"BRAYDEN ROBERTS","a":"0.71"},{"n":"QUENTIN ROBERTS","a":"0.71"},{"n":"DECLAN WHITE","a":"0.70"},{"n":"JAMIE SAMPSON","a":"0.70"},{"n":"PAUL MELLEN","a":"0.70"},{"n":"TOM MALZARD","a":"0.68"},{"n":"MITCHELL FAZEKAS","a":"0.67"},{"n":"SHANE HEATLEY","a":"0.67"},{"n":"THOMAS CHAPMAN","a":"0.67"},{"n":"SAMUEL NAPIER","a":"0.63"},{"n":"DANIEL NESTOR","a":"0.61"},{"n":"SAMUEL THARALDSEN","a":"0.60"},{"n":"ANTHONY BROWNE","a":"0.59"},{"n":"DANIEL NASH","a":"0.58"},{"n":"JOSHUA FARMER","a":"0.58"},{"n":"SCOTT KUMNICK","a":"0.57"},{"n":"THOMAS HAGIAS","a":"0.57"},{"n":"WAYNE COLLINGS","a":"0.57"},{"n":"ANGUS FISHER","a":"0.57"},{"n":"JUSTIN SPRATT","a":"0.57"},{"n":"SHANNON O'CONNOR","a":"0.56"},{"n":"SAUL ABBOTT","a":"0.54"},{"n":"THOMAS DIXON","a":"0.53"},{"n":"MATTHEW WILLOUGHBY","a":"0.53"}]}