{"milestones":[{"name":"150 A Grade Games","grade":"A Grade","type":"Games","recent":[{"Id":3915,"n":"BRAD KIRK","a":152},{"Id":2811,"n":"MICHAEL SHEARER","a":159}]},{"name":"100 A Grade Games","grade":"A Grade","type":"Games","recent":[{"Id":3119,"n":"BRADLEY PATTERSON","a":118},{"Id":2826,"n":"BRAYDEN HEYWARD-FERORS","a":130}]},{"name":"50 A Grade Games","grade":"A Grade","type":"Games","upcoming":[{"Id":2323,"n":"LEIGH O'MALLEY","a":48},{"Id":2867,"n":"NATHAN BEENHAM","a":48},{"Id":2934,"n":"DECLAN TOMKINS","a":47}],"recent":[{"Id":2583,"n":"ANGUS FISHER","a":50},{"Id":2871,"n":"KOBE CAVOURAS","a":55},{"Id":3037,"n":"MACKENZIE SHORT","a":62},{"Id":4106,"n":"NASH MITCHELL","a":55},{"Id":3099,"n":"RYAN MOUNTFORD","a":75}]},{"name":"350 Senior Games","grade":"Senior","type":"Games","recent":[{"Id":2576,"n":"DANIEL CRISA","a":358}]},{"name":"300 Senior Games","grade":"Senior","type":"Games","recent":[{"Id":2479,"n":"DAVID KEARSLEY","a":302}]},{"name":"250 Senior Games","grade":"Senior","type":"Games","recent":[{"Id":2583,"n":"ANGUS FISHER","a":253},{"Id":2175,"n":"KANE ABBOTT","a":258}]},{"name":"200 Senior Games","grade":"Senior","type":"Games","upcoming":[{"Id":2740,"n":"HUW CHANNING","a":199}]},{"name":"150 Senior Games","grade":"Senior","type":"Games","upcoming":[{"Id":2466,"n":"BEN COONEY","a":147}],"recent":[{"Id":2780,"n":"BLAISE TOMKINS","a":178},{"Id":3915,"n":"BRAD KIRK","a":152},{"Id":2826,"n":"BRAYDEN HEYWARD-FERORS","a":155},{"Id":2546,"n":"CAMERON O'MALLEY","a":158},{"Id":2811,"n":"MICHAEL SHEARER","a":160},{"Id":2456,"n":"PAUL ATS","a":150},{"Id":2540,"n":"TIM MEINECKE","a":174}]},{"name":"100 Senior Games","grade":"Senior","type":"Games","upcoming":[{"Id":2798,"n":"LUKE ABBOTT","a":98},{"Id":3426,"n":"SAMUEL THARALDSEN","a":98},{"Id":2871,"n":"KOBE CAVOURAS","a":97},{"Id":2653,"n":"SIMON MURTON","a":95}],"recent":[{"Id":3854,"n":"ALI BALTAGIE","a":105},{"Id":3119,"n":"BRADLEY PATTERSON","a":125},{"Id":2735,"n":"HARRISON GEBHARDT","a":107},{"Id":2911,"n":"MATTHEW CAIRE","a":103},{"Id":2953,"n":"MATTHEW HUNTER","a":102},{"Id":4106,"n":"NASH MITCHELL","a":100},{"Id":3873,"n":"NICK BAILEY","a":105}]},{"name":"50 Senior Games","grade":"Senior","type":"Games","upcoming":[{"Id":2885,"n":"DANIEL NASH","a":49},{"Id":4326,"n":"BRADLEY NOTTLE-JUSTICE","a":48},{"Id":3685,"n":"JACKSON WILLIAMS","a":48},{"Id":4282,"n":"MATTHEW WALTON","a":45}],"recent":[{"Id":3855,"n":"AHMAD BALTAGIE","a":58},{"Id":4291,"n":"ALANA BAKER","a":61},{"Id":3044,"n":"ALEX BUERSCH","a":52},{"Id":3061,"n":"BAXTER KNUCKEY","a":60},{"Id":4331,"n":"BENJAMIN HAWKINS","a":56},{"Id":3535,"n":"BRADLEY JENKE","a":61},{"Id":4233,"n":"ELISE WINTON","a":70},{"Id":3406,"n":"ETHAN WILDMAN","a":76},{"Id":3093,"n":"JAKE BUNWORTH","a":81},{"Id":4318,"n":"KELSEY RODMAN","a":63},{"Id":2900,"n":"LUKE STEWART","a":61},{"Id":3037,"n":"MACKENZIE SHORT","a":78},{"Id":2867,"n":"NATHAN BEENHAM","a":55},{"Id":4296,"n":"NICOLE O'CONNOR","a":65},{"Id":4366,"n":"RACHEL CROCKART","a":50},{"Id":3557,"n":"TODD ALEXANDER","a":59},{"Id":3180,"n":"TRISTAN SMITH","a":51}]},{"name":"400 Club Games","grade":"Club","type":"Games","upcoming":[{"Id":2479,"n":"DAVID KEARSLEY","a":396}],"recent":[{"Id":2323,"n":"LEIGH O'MALLEY","a":409}]},{"name":"350 Club Games","grade":"Club","type":"Games","recent":[{"Id":2583,"n":"ANGUS FISHER","a":357},{"Id":2576,"n":"DANIEL CRISA","a":358},{"Id":2176,"n":"SAUL ABBOTT","a":353}]},{"name":"250 Club Games","grade":"Club","type":"Games","upcoming":[{"Id":3119,"n":"BRADLEY PATTERSON","a":249},{"Id":2546,"n":"CAMERON O'MALLEY","a":249}],"recent":[{"Id":2780,"n":"BLAISE TOMKINS","a":284},{"Id":2826,"n":"BRAYDEN HEYWARD-FERORS","a":278},{"Id":2740,"n":"HUW CHANNING","a":250},{"Id":2734,"n":"JAMIE DELL","a":255},{"Id":2540,"n":"TIM MEINECKE","a":250}]},{"name":"200 Club Games","grade":"Club","type":"Games","recent":[{"Id":2934,"n":"DECLAN TOMKINS","a":219},{"Id":2735,"n":"HARRISON GEBHARDT","a":202},{"Id":2871,"n":"KOBE CAVOURAS","a":209},{"Id":2908,"n":"LUKE BEENHAM","a":219},{"Id":2953,"n":"MATTHEW HUNTER","a":225}]},{"name":"150 Club Games","grade":"Club","type":"Games","upcoming":[{"Id":2867,"n":"NATHAN BEENHAM","a":147},{"Id":3073,"n":"TYLER WARREN","a":147}],"recent":[{"Id":3855,"n":"AHMAD BALTAGIE","a":177},{"Id":3044,"n":"ALEX BUERSCH","a":156},{"Id":3854,"n":"ALI BALTAGIE","a":151},{"Id":3061,"n":"BAXTER KNUCKEY","a":162},{"Id":3178,"n":"BLAKE ALDRIDGE","a":178},{"Id":3915,"n":"BRAD KIRK","a":152},{"Id":2778,"n":"BRADLEY DRAPER","a":158},{"Id":3406,"n":"ETHAN WILDMAN","a":174},{"Id":3093,"n":"JAKE BUNWORTH","a":177},{"Id":3291,"n":"JOSHUA FAIZAL","a":164},{"Id":3037,"n":"MACKENZIE SHORT","a":158},{"Id":2811,"n":"MICHAEL SHEARER","a":160},{"Id":3405,"n":"MITCHELL JOHNSON","a":156},{"Id":3920,"n":"MOUSTUFA BALTAGIE","a":164},{"Id":2456,"n":"PAUL ATS","a":150},{"Id":4023,"n":"TOBY RUSSELL","a":165},{"Id":3180,"n":"TRISTAN SMITH","a":161}]},{"name":"100 Club Games","grade":"Club","type":"Games","upcoming":[{"Id":2590,"n":"RYAN INGRAM","a":99},{"Id":2859,"n":"REECE MILSOM","a":98},{"Id":3535,"n":"BRADLEY JENKE","a":97},{"Id":4209,"n":"BRODIE SISSON","a":96},{"Id":4309,"n":"EMMA HODGSON","a":96},{"Id":4208,"n":"JACOB COMLEY","a":96}],"recent":[{"Id":3250,"n":"ADAM BUNWORTH","a":113},{"Id":3220,"n":"BAILEY RICHMAN","a":115},{"Id":3175,"n":"BEN BURBRIDGE","a":105},{"Id":3450,"n":"COOPER AMES","a":124},{"Id":3569,"n":"JACKSON COSTELLO","a":118},{"Id":3685,"n":"JACKSON WILLIAMS","a":129},{"Id":3375,"n":"JAMES BRENNAN","a":112},{"Id":4076,"n":"JAMES KEATING","a":103},{"Id":4066,"n":"LEITH (JNR) MITCHELL","a":100},{"Id":4106,"n":"NASH MITCHELL","a":100},{"Id":3873,"n":"NICK BAILEY","a":105},{"Id":3451,"n":"RILEY STONE","a":124},{"Id":3426,"n":"SAMUEL THARALDSEN","a":106},{"Id":3290,"n":"TYLER HALLIDAY","a":107}]},{"name":"50 Club Games","grade":"Club","type":"Games","upcoming":[{"Id":4378,"n":"SASHA NANCARROW","a":49},{"Id":4405,"n":"BELLA NICHOLLS-NEWMAN","a":48},{"Id":4326,"n":"BRADLEY NOTTLE-JUSTICE","a":48},{"Id":4413,"n":"EMMA JEFFRIES","a":48},{"Id":4416,"n":"JACK CHAPLIN","a":48},{"Id":3831,"n":"TYCE LUSH","a":48},{"Id":4351,"n":"DYLAN SMITH","a":47},{"Id":4407,"n":"ALYSSA MARLOW","a":46},{"Id":3678,"n":"HARRISON SLATTERY","a":46},{"Id":4186,"n":"TAIYA RENFREY","a":46},{"Id":3035,"n":"WILLIAM NASH","a":46},{"Id":4412,"n":"CLAIRE BRYANT","a":45},{"Id":4282,"n":"MATTHEW WALTON","a":45}],"recent":[{"Id":3050,"n":"ADAM KLEINIG","a":60},{"Id":4348,"n":"AIDEN GRAYSON","a":64},{"Id":4055,"n":"ALAA EL-DIN BALTAGIE","a":73},{"Id":4291,"n":"ALANA BAKER","a":61},{"Id":4404,"n":"AVA KNUCKEY","a":52},{"Id":4331,"n":"BENJAMIN HAWKINS","a":56},{"Id":4304,"n":"BROOKE WATSON","a":57},{"Id":3689,"n":"CALLAN COATS","a":51},{"Id":4276,"n":"CALLUM TROTT","a":58},{"Id":4350,"n":"CAMERON NUSKE","a":66},{"Id":4313,"n":"CASCIA SMAILES","a":54},{"Id":3834,"n":"COBY HIBBERT","a":57},{"Id":4233,"n":"ELISE WINTON","a":70},{"Id":4307,"n":"GABRIELLA BAKER","a":71},{"Id":4308,"n":"IMOGEN RUSSELL","a":82},{"Id":4273,"n":"JACK BISHOP","a":55},{"Id":4337,"n":"JAMES HELE","a":54},{"Id":4270,"n":"JETT CARLIER","a":58},{"Id":4272,"n":"JOSHUA LEES","a":84},{"Id":4414,"n":"KAHLIA READ","a":53},{"Id":3527,"n":"KAITLYN ALDRIDGE","a":62},{"Id":4318,"n":"KELSEY RODMAN","a":63},{"Id":4415,"n":"KYAH SMITH","a":50},{"Id":2900,"n":"LUKE STEWART","a":61},{"Id":3988,"n":"MAX CLIFTON","a":50},{"Id":4354,"n":"MELISSA ANDERSON","a":50},{"Id":4417,"n":"MITCHELL CHAPLIN","a":51},{"Id":4296,"n":"NICOLE O'CONNOR","a":65},{"Id":3757,"n":"PETER ROBJOHNS","a":51},{"Id":4329,"n":"PEYTON BROOKES","a":62},{"Id":4366,"n":"RACHEL CROCKART","a":50},{"Id":3766,"n":"SIENNA ALDRIDGE","a":63},{"Id":4227,"n":"SIENNA CHAPMAN","a":72},{"Id":4371,"n":"SOPHIE HODGSON","a":59},{"Id":4003,"n":"TAAID FALLAH","a":58},{"Id":4324,"n":"TIA TAYLOR","a":70},{"Id":3557,"n":"TODD ALEXANDER","a":59},{"Id":4370,"n":"ZOE HODGSON","a":66}]},{"name":"100 Junior Games","grade":"Junior","type":"Games","upcoming":[{"Id":3867,"n":"SALEH BALTAGIE","a":98},{"Id":4209,"n":"BRODIE SISSON","a":96}],"recent":[{"Id":3569,"n":"JACKSON COSTELLO","a":114},{"Id":4076,"n":"JAMES KEATING","a":101},{"Id":3451,"n":"RILEY STONE","a":113}]},{"name":"50 Junior Games","grade":"Junior","type":"Games","upcoming":[{"Id":4417,"n":"MITCHELL CHAPLIN","a":49},{"Id":4350,"n":"CAMERON NUSKE","a":48},{"Id":4413,"n":"EMMA JEFFRIES","a":48},{"Id":4416,"n":"JACK CHAPLIN","a":48},{"Id":3831,"n":"TYCE LUSH","a":48},{"Id":4351,"n":"DYLAN SMITH","a":47},{"Id":4407,"n":"ALYSSA MARLOW","a":46},{"Id":3678,"n":"HARRISON SLATTERY","a":46},{"Id":4186,"n":"TAIYA RENFREY","a":46},{"Id":3035,"n":"WILLIAM NASH","a":46},{"Id":4412,"n":"CLAIRE BRYANT","a":45}],"recent":[{"Id":4055,"n":"ALAA EL-DIN BALTAGIE","a":56},{"Id":3689,"n":"CALLAN COATS","a":51},{"Id":4276,"n":"CALLUM TROTT","a":58},{"Id":4313,"n":"CASCIA SMAILES","a":54},{"Id":3834,"n":"COBY HIBBERT","a":57},{"Id":4307,"n":"GABRIELLA BAKER","a":67},{"Id":4308,"n":"IMOGEN RUSSELL","a":56},{"Id":4273,"n":"JACK BISHOP","a":55},{"Id":4337,"n":"JAMES HELE","a":53},{"Id":4270,"n":"JETT CARLIER","a":58},{"Id":4272,"n":"JOSHUA LEES","a":83},{"Id":4414,"n":"KAHLIA READ","a":53},{"Id":3527,"n":"KAITLYN ALDRIDGE","a":55},{"Id":4415,"n":"KYAH SMITH","a":50},{"Id":3757,"n":"PETER ROBJOHNS","a":51},{"Id":4329,"n":"PEYTON BROOKES","a":62},{"Id":3766,"n":"SIENNA ALDRIDGE","a":63},{"Id":4371,"n":"SOPHIE HODGSON","a":59},{"Id":4324,"n":"TIA TAYLOR","a":53},{"Id":4370,"n":"ZOE HODGSON","a":66}]},{"name":"250 B Grade Games","grade":"B Grade","type":"Games","recent":[{"Id":2323,"n":"LEIGH O'MALLEY","a":269}]},{"name":"200 B Grade Games","grade":"B Grade","type":"Games","upcoming":[{"Id":2583,"n":"ANGUS FISHER","a":196}]},{"name":"100 B Grade Games","grade":"B Grade","type":"Games","recent":[{"Id":2594,"n":"CRAIG LANGCAKE","a":106},{"Id":2740,"n":"HUW CHANNING","a":102}]},{"name":"250 C Grade Games","grade":"C Grade","type":"Games","recent":[{"Id":2576,"n":"DANIEL CRISA","a":250}]},{"name":"50 C Grade Games","grade":"C Grade","type":"Games","upcoming":[{"Id":4326,"n":"BRADLEY NOTTLE-JUSTICE","a":48},{"Id":3091,"n":"CAMPBELL WRIGHT","a":47}],"recent":[{"Id":4285,"n":"ADRIAN PETERSON","a":61},{"Id":3854,"n":"ALI BALTAGIE","a":81},{"Id":4331,"n":"BENJAMIN HAWKINS","a":56},{"Id":3535,"n":"BRADLEY JENKE","a":58},{"Id":2708,"n":"DECLAN WHITE","a":57},{"Id":2175,"n":"KANE ABBOTT","a":55},{"Id":3920,"n":"MOUSTUFA BALTAGIE","a":62},{"Id":2340,"n":"STUART ATS","a":50}]},{"name":"50 Open Women Games","grade":"Open Women","type":"Games","recent":[{"Id":4291,"n":"ALANA BAKER","a":61},{"Id":4233,"n":"ELISE WINTON","a":70},{"Id":4318,"n":"KELSEY RODMAN","a":63},{"Id":4296,"n":"NICOLE O'CONNOR","a":65},{"Id":4366,"n":"RACHEL CROCKART","a":50}]}]}