{"name":"Most Goals in a Game - C Grade","headers":{"c1":"Name","c2":"Goals"},"data":[{"n":"RICKY DALBY","a":12},{"n":"DANIEL MARKS","a":10},{"n":"JACK MITTIGA","a":9},{"n":"MATT PALFREY","a":9},{"n":"RICKY DALBY","a":9},{"n":"HARRISON GEBHARDT","a":8},{"n":"HARRISON GEBHARDT","a":8},{"n":"JACK MITTIGA","a":8},{"n":"THOMAS SOUTH","a":8},{"n":"ALEX CRISA","a":7},{"n":"BRAYDEN ROBERTS","a":7},{"n":"HARRISON GEBHARDT","a":7},{"n":"JAMES NIKKERUD","a":7},{"n":"LUKE ABBOTT","a":7},{"n":"MATT PALFREY","a":7},{"n":"TIM MEADE","a":7},{"n":"ALEX CRISA","a":6},{"n":"CALLUM ADAMS","a":6},{"n":"DANIEL MARKS","a":6},{"n":"HARRISON GEBHARDT","a":6},{"n":"HARRISON GEBHARDT","a":6},{"n":"JED DOBRE","a":6},{"n":"LUKE ABBOTT","a":6},{"n":"LUKE ABBOTT","a":6},{"n":"LUKE ABBOTT","a":6},{"n":"MATT PALFREY","a":6},{"n":"MATT PALFREY","a":6},{"n":"MATTHEW WRIGHT","a":6},{"n":"NATHAN MIFSUD","a":6},{"n":"RICKY DALBY","a":6},{"n":"THOMAS SOUTH","a":6},{"n":"ALEX CRISA","a":5},{"n":"ALEX CRISA","a":5},{"n":"ALI BALTAGIE","a":5},{"n":"BRADLEY MORRISON","a":5},{"n":"CAMPBELL WRIGHT","a":5},{"n":"CAMPBELL WRIGHT","a":5},{"n":"HARRISON GEBHARDT","a":5},{"n":"HARRISON GEBHARDT","a":5},{"n":"JACK MITTIGA","a":5},{"n":"JOSH  BRETT","a":5},{"n":"LUKE ABBOTT","a":5},{"n":"LUKE ABBOTT","a":5},{"n":"LUKE ABBOTT","a":5},{"n":"MICHAEL HASLAM","a":5},{"n":"MITCHELL JOHNSON","a":5},{"n":"NATHAN MIFSUD","a":5},{"n":"RICKY DALBY","a":5},{"n":"RICKY DALBY","a":5},{"n":"RICKY DALBY","a":5},{"n":"SIMON MURTON","a":5},{"n":"THOMAS SOUTH","a":5},{"n":"TIM MEADE","a":5},{"n":"TOM MALZARD","a":5},{"n":"ADAM SHIPARD","a":4},{"n":"ALEX CRISA","a":4},{"n":"ALEX CRISA","a":4},{"n":"ALEX CRISA","a":4},{"n":"ALEX CRISA","a":4},{"n":"ALEX CRISA","a":4},{"n":"ALEX CRISA","a":4},{"n":"ALI BALTAGIE","a":4},{"n":"ANDREW LIVERTON","a":4},{"n":"CALLUM ADAMS","a":4},{"n":"CHOL MAJOK","a":4},{"n":"CHOL MAJOK","a":4},{"n":"DANIEL MARKS","a":4},{"n":"DANIEL ZANDONA","a":4},{"n":"HARRISON GEBHARDT","a":4},{"n":"HARRISON GEBHARDT","a":4},{"n":"JACK MITTIGA","a":4},{"n":"JACK MITTIGA","a":4},{"n":"JACK MITTIGA","a":4},{"n":"JACK MITTIGA","a":4},{"n":"JACK MITTIGA","a":4},{"n":"JACK MITTIGA","a":4},{"n":"JAMES ROBSHAW","a":4},{"n":"JAMIE DELL","a":4},{"n":"JORDAN SELLAR","a":4},{"n":"JOSH  BRETT","a":4},{"n":"KANE ABBOTT","a":4},{"n":"LACHLAN BATES","a":4},{"n":"LACHLAN BATES","a":4},{"n":"LUKE ABBOTT","a":4},{"n":"LUKE HILL","a":4},{"n":"MATT PALFREY","a":4},{"n":"MICHAEL HASLAM","a":4},{"n":"NATHAN MIFSUD","a":4},{"n":"RICKY DALBY","a":4},{"n":"RICKY DALBY","a":4},{"n":"RYAN WILLIAMS","a":4},{"n":"SAMUEL OSMOND","a":4},{"n":"SIMON MURTON","a":4},{"n":"SIMON MURTON","a":4},{"n":"SIMON TROTT","a":4},{"n":"STEVEN GATER","a":4},{"n":"THOMAS BREYNARD","a":4},{"n":"THOMAS SOUTH","a":4},{"n":"THOMAS SOUTH","a":4},{"n":"THOMAS SOUTH","a":4}]}